okta_token_fetcher/__init__.py
okta_token_fetcher/cli.py
okta_token_fetcher-0.1.2.dist-info/METADATA
okta_token_fetcher-0.1.2.dist-info/WHEEL
okta_token_fetcher-0.1.2.dist-info/entry_points.txt
okta_token_fetcher-0.1.2.dist-info/RECORD
