Metadata-Version: 2.1
Name: okta-token-fetcher
Version: 0.1.2
Summary: Used to fetch OKTA tokens for an application using web a browser that redirects to a commandline server
Home-page: https://github.com/mathewmoon/okta-token-fetcher
Author: Mathew Moon
Author-email: me@mathewmoon.net
Requires-Python: >=3.8,<4.0
Classifier: Programming Language :: Python :: 3
Classifier: Programming Language :: Python :: 3.8
Classifier: Programming Language :: Python :: 3.9
Classifier: Programming Language :: Python :: 3.10
Classifier: Programming Language :: Python :: 3.11
Classifier: Programming Language :: Python :: 3.12
Requires-Dist: PyJWT (>=2.8.0,<3.0.0)
Requires-Dist: keyring (>=24.3.0,<25.0.0)
Requires-Dist: requests (>=2.31.0,<3.0.0)
Project-URL: Repository, https://github.com/mathewmoon/okta-token-fetcher
